hf_ms_transfer/__init__.py
hf_ms_transfer/__main__.py
hf_ms_transfer-0.4.1.dist-info/licenses/LICENSE
hf_ms_transfer-0.4.1.dist-info/METADATA
hf_ms_transfer-0.4.1.dist-info/WHEEL
hf_ms_transfer-0.4.1.dist-info/entry_points.txt
hf_ms_transfer-0.4.1.dist-info/top_level.txt
hf_ms_transfer-0.4.1.dist-info/RECORD
