Metadata-Version: 2.4
Name: hf-ms-transfer
Version: 0.4.1
Summary: A tool to transfer models/datasets from Hugging Face to ModelScope
Author-email: wa008 <zphu1024@gmail.com>
Project-URL: Homepage, https://github.com/wa008/hf-ms-transfer
Project-URL: Bug Tracker, https://github.com/wa008/hf-ms-transfer/issues
Classifier: Programming Language :: Python :: 3
Classifier: License :: OSI Approved :: MIT License
Classifier: Operating System :: OS Independent
Requires-Python: >=3.6
License-File: LICENSE
Requires-Dist: huggingface_hub
Requires-Dist: modelscope
Requires-Dist: python-dotenv
Dynamic: license-file
